takopi_ralph/__init__.py
takopi_ralph/analysis/__init__.py
takopi_ralph/analysis/analyzer.py
takopi_ralph/analysis/status_parser.py
takopi_ralph/circuit_breaker/__init__.py
takopi_ralph/circuit_breaker/breaker.py
takopi_ralph/clarify/__init__.py
takopi_ralph/clarify/flow.py
takopi_ralph/clarify/llm_analyzer.py
takopi_ralph/clarify/prompt_loader.py
takopi_ralph/clarify/templates/create.md
takopi_ralph/clarify/templates/enhance.md
takopi_ralph/clarify/templates/enhance_focused.md
takopi_ralph/clarify/templates/quality_library.md
takopi_ralph/clarify/templates/quality_production.md
takopi_ralph/clarify/templates/quality_prototype.md
takopi_ralph/clarify/templates/ralph_status.md
takopi_ralph/clarify/templates/system.md
takopi_ralph/clarify/templates/with_answers.md
takopi_ralph/command/__init__.py
takopi_ralph/command/backend.py
takopi_ralph/command/context.py
takopi_ralph/command/handlers/__init__.py
takopi_ralph/command/handlers/clarify.py
takopi_ralph/command/handlers/init.py
takopi_ralph/command/handlers/prd.py
takopi_ralph/command/handlers/reset.py
takopi_ralph/command/handlers/start.py
takopi_ralph/command/handlers/status.py
takopi_ralph/command/handlers/stop.py
takopi_ralph/engine/__init__.py
takopi_ralph/engine/backend.py
takopi_ralph/engine/prompt_augmenter.py
takopi_ralph/engine/runner.py
takopi_ralph/init/__init__.py
takopi_ralph/init/flow.py
takopi_ralph/prd/__init__.py
takopi_ralph/prd/manager.py
takopi_ralph/prd/schema.py
takopi_ralph/state/__init__.py
takopi_ralph/state/manager.py
takopi_ralph/state/models.py
takopi_ralph-0.3.0.dist-info/METADATA
takopi_ralph-0.3.0.dist-info/WHEEL
takopi_ralph-0.3.0.dist-info/entry_points.txt
takopi_ralph-0.3.0.dist-info/licenses/LICENSE
takopi_ralph-0.3.0.dist-info/RECORD
