Metadata-Version: 2.4
Name: takopi-ralph
Version: 0.3.0
Summary: Autonomous coding loop plugin for Takopi - PRD-driven development with circuit breaker protection
Project-URL: Homepage, https://github.com/l3wi/takopi-ralph
Project-URL: Repository, https://github.com/l3wi/takopi-ralph
Project-URL: Issues, https://github.com/l3wi/takopi-ralph/issues
Author-email: Lewis Freiberg <lewis@freiberg.dev>
License: MIT License
License-File: LICENSE
Keywords: ai,autonomous,claude,coding,development,llm,plugin,takopi
Classifier: Development Status :: 3 - Alpha
Classifier: Environment :: Console
Classifier: Intended Audience :: Developers
Classifier: License :: OSI Approved :: MIT License
Classifier: Operating System :: OS Independent
Classifier: Programming Language :: Python :: 3
Classifier: Programming Language :: Python :: 3 :: Only
Classifier: Programming Language :: Python :: 3.14
Classifier: Topic :: Software Development
Classifier: Topic :: Software Development :: Code Generators
Classifier: Typing :: Typed
Requires-Python: >=3.14
Requires-Dist: anyio>=4.8.0
Requires-Dist: pydantic>=2.10
Requires-Dist: takopi>=0.15
